setup.py
distributions_DH/Binomialdistribution.py
distributions_DH/Gaussiandistribution.py
distributions_DH/Generaldistribution.py
distributions_DH/__init__.py
distributions_DH.egg-info/PKG-INFO
distributions_DH.egg-info/SOURCES.txt
distributions_DH.egg-info/dependency_links.txt
distributions_DH.egg-info/not-zip-safe
distributions_DH.egg-info/top_level.txt